penguin_analyst_sharon/__init__.py
penguin_analyst_sharon/main.py
penguin_analyst_sharon-0.1.1.dist-info/METADATA
penguin_analyst_sharon-0.1.1.dist-info/WHEEL
penguin_analyst_sharon-0.1.1.dist-info/RECORD
