Metadata-Version: 2.1
Name: penguin-analyst-sharon
Version: 0.1.1
Summary: 
Author: SHARONOFER
Author-email: 35968217+SHARONOFER@users.noreply.github.com
Requires-Python: >=3.8,<4.0
Classifier: Programming Language :: Python :: 3
Classifier: Programming Language :: Python :: 3.8
Classifier: Programming Language :: Python :: 3.9
Classifier: Programming Language :: Python :: 3.10
Classifier: Programming Language :: Python :: 3.11
Requires-Dist: pandas (>=1.5.3,<2.0.0)
